ahi/__init__.py
ahi/cli/__init__.py
ahi/cli/backtrack.py
ahi/cli/http.py
ahi/cli/openapi.py
ahi/cli/postman.py
ahi/cli/scaffolding.py
ahi/common.py
ahi/response.py
ahi/selenium_chrome.py
ahi/selenium_firefox.py
ahi/simple.py
ahi-0.19.38.dist-info/LICENSE
ahi-0.19.38.dist-info/METADATA
ahi-0.19.38.dist-info/WHEEL
ahi-0.19.38.dist-info/entry_points.txt
ahi-0.19.38.dist-info/RECORD
