Metadata-Version: 2.3
Name: ahi
Version: 0.19.38
Summary: Application Hacking Interface. An HTTP API client helper for "unofficial" APIs.
License: LGPL-3.0-or-later
Author: beruu
Author-email: 18537787-beruu@users.noreply.gitlab.com
Requires-Python: >=3.9.0
Classifier: Development Status :: 4 - Beta
Classifier: License :: OSI Approved :: GNU Lesser General Public License v3 or later (LGPLv3+)
Classifier: Programming Language :: Python :: 3
Classifier: Programming Language :: Python :: 3.9
Classifier: Programming Language :: Python :: 3.10
Classifier: Programming Language :: Python :: 3.11
Classifier: Programming Language :: Python :: 3.12
Classifier: Programming Language :: Python :: 3.13
Classifier: Topic :: Internet :: WWW/HTTP
Classifier: Topic :: Software Development :: Testing
Provides-Extra: browser-emulation
Requires-Dist: PySocks (>=1.7.1)
Requires-Dist: hiredis (>=2.0.0)
Requires-Dist: parsel (>=1.6.0)
Requires-Dist: redis (>=3.5.3)
Requires-Dist: requests (>=2.26.0,<3.0.0)
Requires-Dist: selenium (>=4.0.0,<5.0.0) ; extra == "browser-emulation"
Requires-Dist: urllib3 (>=2.0.0,<3.0.0)
Project-URL: Homepage, https://gitlab.com/unsanctioned/ahi
